cRun_py/cRun.py
src/cRun.py
crun_py-0.0.5.dist-info/LICENSE.txt
crun_py-0.0.5.dist-info/METADATA
crun_py-0.0.5.dist-info/WHEEL
crun_py-0.0.5.dist-info/entry_points.txt
crun_py-0.0.5.dist-info/top_level.txt
crun_py-0.0.5.dist-info/RECORD
