Metadata-Version: 2.1
Name: crun-py
Version: 0.0.5
Summary: C Programming Simplified
Home-page: https://get-crun.github.io/
Author: Snehashis Sarkar
Author-email: snehashis.2000@gmail.com
License: UNKNOWN
Project-URL: GitHub repository, https://github.com/snehashis365/cRun-py
Platform: UNKNOWN
Classifier: Programming Language :: Python :: 3
Classifier: Programming Language :: Python :: 3.6
Classifier: License :: OSI Approved :: MIT License
Classifier: Development Status :: 3 - Alpha
Classifier: Operating System :: POSIX :: Linux
Classifier: Operating System :: MacOS
Classifier: Operating System :: Microsoft :: Windows :: Windows 10
Classifier: Operating System :: Android
Requires-Python: >=3.6
Requires-Dist: tqdm
Requires-Dist: windows-curses (>=2.0) ; platform_system == "Windows"
